polarstate/__init__.py
polarstate/aj.py
polarstate/predict.py
polarstate-0.1.8.dist-info/WHEEL
polarstate-0.1.8.dist-info/entry_points.txt
polarstate-0.1.8.dist-info/METADATA
polarstate-0.1.8.dist-info/RECORD
