Metadata-Version: 2.3
Name: polarstate
Version: 0.1.8
Summary: Add your description here
Author: Uriah Finkel
Author-email: Uriah Finkel <Ufinkel@gmail.com>
Requires-Dist: polars>=1.30.0
Requires-Python: >=3.9
